bbg_api_controller/__init__.py
bbg_api_controller/application.py
bbg_api_controller/composed.py
bbg_api_controller/connector.py
bbg_api_controller/utils.py
bbg_api_controller/basis/__init__.py
bbg_api_controller/basis/fetcher.py
bbg_api_controller/basis/functionals.py
bbg_api_controller/basis/utils.py
bbg_api_controller/consts/__init__.py
bbg_api_controller/consts/bbg_consts.py
bbg_api_controller/consts/db_consts.py
bbg_api_controller/consts/general.py
bbg_api_controller-0.1.2.dist-info/METADATA
bbg_api_controller-0.1.2.dist-info/WHEEL
bbg_api_controller-0.1.2.dist-info/top_level.txt
bbg_api_controller-0.1.2.dist-info/RECORD
