Metadata-Version: 2.4
Name: bbg_api_controller
Version: 0.1.2
Summary: A Python package providing utility functions for bbg api controller
Author: June Young Park
Author-email: juneyoungpaak@gmail.com
Classifier: Programming Language :: Python :: 3
Classifier: Programming Language :: Python :: 3.7
Classifier: Programming Language :: Python :: 3.8
Classifier: Programming Language :: Python :: 3.9
Classifier: Programming Language :: Python :: 3.10
Requires-Python: >=3.7
Requires-Dist: pdblp
Requires-Dist: pandas
Requires-Dist: tqdm
Requires-Dist: python-dotenv
Requires-Dist: canonical_transformer
Requires-Dist: string_date_controller
Requires-Dist: shining_pebbles
Requires-Dist: mongodb_controller
Dynamic: author
Dynamic: author-email
Dynamic: classifier
Dynamic: description
Dynamic: description-content-type
Dynamic: requires-dist
Dynamic: requires-python
Dynamic: summary
